sudo_win32/__init__.py
sudo_win32/cli.py
sudo_win32/elevated_exec.py
sudo_win32/gsudo.7z
sudo_win32/install.py
sudo_win32/gsudo/Invoke-gsudo.ps1
sudo_win32/gsudo/gsudo
sudo_win32/gsudo/gsudo.exe
sudo_win32/gsudo/gsudo.exe.ignore
sudo_win32/gsudo/gsudoModule.psd1
sudo_win32/gsudo/gsudoModule.psm1
sudo_win32-1.0.9.dist-info/LICENSE
sudo_win32-1.0.9.dist-info/METADATA
sudo_win32-1.0.9.dist-info/WHEEL
sudo_win32-1.0.9.dist-info/entry_points.txt
sudo_win32-1.0.9.dist-info/top_level.txt
sudo_win32-1.0.9.dist-info/RECORD
