Metadata-Version: 2.1
Name: sudo-win32
Version: 1.0.9
Summary: The missing sudo command for win32
Home-page: https://github.com/zackees/sudo-win32
Maintainer: Zachary Vorhies
License: BSD 3-Clause License
Keywords: template-python-cmd
Classifier: Programming Language :: Python :: 3
Requires-Python: >=3.7
License-File: LICENSE
Requires-Dist: py7zr
Provides-Extra: sudo
Requires-Dist: sudo-win32-extras ; extra == 'sudo'
